RicianLoss/__init__.py
RicianLoss/setup.py
RicianLoss/data/__init__.py
RicianLoss/data/notes.txt
RicianLoss/data/real_data.pkl
RicianLoss/data/simulated_data.pkl
RicianLoss/examples/__init__.py
RicianLoss/examples/example_qmri.py
RicianLoss/lossfuncs/__init__.py
RicianLoss/lossfuncs/lossfuncs.py
RicianLoss/modelfuncs/__init__.py
RicianLoss/modelfuncs/modelfuncs.py
RicianLoss/nnfuncs/__init__.py
RicianLoss/nnfuncs/nnfuncs.py
RicianLoss/sigma/__init__.py
RicianLoss/sigma/sigma.py
RicianLoss/tests/__init__.py
RicianLoss/utils/__init__.py
RicianLoss/utils/utils.py
ricianloss-0.0.1.dist-info/METADATA
ricianloss-0.0.1.dist-info/WHEEL
ricianloss-0.0.1.dist-info/licenses/LICENSE.txt
ricianloss-0.0.1.dist-info/RECORD
